[
 {
  "ID": 1,
  "Departamento": "Recepção",
  "Responsáveis": "Colaborador Externo",
  "Ramal": 9999
 },
 {
  "ID": 2,
  "Departamento": "Marketing",
  "Responsáveis": "Colaborador Externo",
  "Ramal": 9999
 },
 {
  "ID": 3,
  "Departamento": "Ass. Compras",
  "Responsáveis": "Colaborador Externo",
  "Ramal": 9999
 },
 {
  "ID": 4,
  "Departamento": "Aux. Compras",
  "Responsáveis": "Colaborador Externo",
  "Ramal": 9999
 },
 {
  "ID": 5,
  "Departamento": "Comprador",
  "Responsáveis": "Colaborador Externo",
  "Ramal": 9999
 },
 {
  "ID": 6,
  "Departamento": "Ass. Compras",
  "Responsáveis": "Colaborador Externo",
  "Ramal": 9999
 },
 {
  "ID": 7,
  "Departamento": "Regional",
  "Responsáveis": "Colaborador Externo",
  "Ramal": 9999
 },
 {
  "ID": 8,
  "Departamento": "Design",
  "Responsáveis": "Colaborador Externo",
  "Ramal": 9999
 },
 {
  "ID": 9,
  "Departamento": "Ass. Compras",
  "Responsáveis": "Colaborador Externo",
  "Ramal": 9999
 },
 {
  "ID": 10,
  "Departamento": "Aux. Compras",
  "Responsáveis": "Colaborador Externo",
  "Ramal": 9999
 },
 {
  "ID": 11,
  "Departamento": "Comprador",
  "Responsáveis": "Colaborador Externo",
  "Ramal": 9999
 },
 {
  "ID": 12,
  "Departamento": "Suporte Redes",
  "Responsáveis": "Colaborador Externo",
  "Ramal": 9999
 },
 {
  "ID": 13,
  "Departamento": "Comprador",
  "Responsáveis": "Colaborador Externo",
  "Ramal": 9999
 },
 {
  "ID": 14,
  "Departamento": "Aux. Compras",
  "Responsáveis": "Colaborador Externo",
  "Ramal": 9999
 },
 {
  "ID": 15,
  "Departamento": "Técnico RUB",
  "Responsáveis": "Colaborador Externo",
  "Ramal": 9999
 },
 {
  "ID": 16,
  "Departamento": "Ass. Compras",
  "Responsáveis": "Colaborador Externo",
  "Ramal": 9999
 },
 {
  "ID": 17,
  "Departamento": "Aux. Compras",
  "Responsáveis": "Colaborador Externo",
  "Ramal": 9999
 },
 {
  "ID": 18,
  "Departamento": "Comprador",
  "Responsáveis": "Colaborador Externo",
  "Ramal": 9999
 },
 {
  "ID": 19,
  "Departamento": "Ass. Compras",
  "Responsáveis": "Colaborador Externo",
  "Ramal": 9999
 },
 {
  "ID": 20,
  "Departamento": "Aux. Compras",
  "Responsáveis": "Colaborador Externo",
  "Ramal": 9999
 },
 {
  "ID": 21,
  "Departamento": "Comprador",
  "Responsáveis": "Colaborador Externo",
  "Ramal": 9999
 },
 {
  "ID": 22,
  "Departamento": "Ass. Compras",
  "Responsáveis": "Colaborador Externo",
  "Ramal": 9999
 },
 {
  "ID": 23,
  "Departamento": "Aux. Compras",
  "Responsáveis": "Colaborador Externo",
  "Ramal": 9999
 },
 {
  "ID": 24,
  "Departamento": "Comprador",
  "Responsáveis": "Colaborador Externo",
  "Ramal": 9999
 }
]